stPlus/__init__.py
stPlus/dataset.py
stPlus/loss.py
stPlus/model.py
stPlus/utils.py
stPlus-0.0.6.dist-info/LICENSE
stPlus-0.0.6.dist-info/METADATA
stPlus-0.0.6.dist-info/WHEEL
stPlus-0.0.6.dist-info/top_level.txt
stPlus-0.0.6.dist-info/RECORD
